claude_lfr_mcp/__init__.py
claude_lfr_mcp/ignore.py
claude_lfr_mcp/indexer.py
claude_lfr_mcp/mcp_server.py
claude_lfr_mcp/models.py
claude_lfr_mcp/searcher.py
claude_lfr_mcp-0.1.0.dist-info/licenses/LICENSE
claude_lfr_mcp-0.1.0.dist-info/METADATA
claude_lfr_mcp-0.1.0.dist-info/WHEEL
claude_lfr_mcp-0.1.0.dist-info/entry_points.txt
claude_lfr_mcp-0.1.0.dist-info/top_level.txt
claude_lfr_mcp-0.1.0.dist-info/RECORD
