Metadata-Version: 2.4
Name: claude-lfr-mcp
Version: 0.1.0
Summary: Fast CPU-based RAG for codebases using BGE embeddings and Qdrant. MCP server for Claude Code.
Author-email: Maik Derstappen <md@derico.de>
License-Expression: MIT
Project-URL: Repository, https://gitlab.com/derico/claude-lfr-mcp
Project-URL: Issues, https://gitlab.com/derico/claude-lfr-mcp/-/issues
Keywords: rag,code-search,embeddings,qdrant,mcp,claude-code,semantic-search,bge,vector-database,cpu-inference
Classifier: Development Status :: 4 - Beta
Classifier: Environment :: Console
Classifier: Intended Audience :: Developers
Classifier: Programming Language :: Python :: 3
Classifier: Programming Language :: Python :: 3.10
Classifier: Programming Language :: Python :: 3.11
Classifier: Programming Language :: Python :: 3.12
Classifier: Topic :: Software Development :: Libraries :: Python Modules
Classifier: Topic :: Text Processing :: Indexing
Requires-Python: >=3.10
License-File: LICENSE
Requires-Dist: qdrant-client>=1.9.0
Requires-Dist: torch>=2.2.0
Requires-Dist: transformers>=4.40.0
Requires-Dist: accelerate>=0.30.0
Requires-Dist: mcp>=1.0.0
Requires-Dist: pathspec>=0.12.0
Provides-Extra: dev
Requires-Dist: pytest>=8.0.0; extra == "dev"
Requires-Dist: pytest-asyncio>=0.24.0; extra == "dev"
Requires-Dist: pytest-cov>=4.1.0; extra == "dev"
Requires-Dist: pytest-mock>=3.12.0; extra == "dev"
Dynamic: license-file
